{
  "player_id": 8476872,
  "basic_info": {
    "name": "Scott Laughton",
    "first_name": "Scott",
    "last_name": "Laughton",
    "jersey_number": 24,
    "position": "L",
    "team_abbrev": "TOR",
    "team_name": "Toronto Maple Leafs",
    "height_inches": 73,
    "weight_pounds": 191,
    "birth_date": "1994-05-30",
    "birth_city": "Oakville",
    "birth_country": "CAN",
    "shoots_catches": "L",
    "headshot": "https://assets.nhle.com/mugs/nhl/20242025/TOR/8476872.png",
    "is_active": true
  },
  "draft_info": {
    "year": 2012,
    "teamAbbrev": "PHI",
    "round": 1,
    "pickInRound": 20,
    "overallPick": 20
  },
  "awards": [],
  "updated": "2025-05-30T23:10:24.797657",
  "current_season_stats": {
    "season": 20082009,
    "league": "OHF Bantam AAA",
    "team": "Toronto Marlboros Bantam AAA",
    "games_played": 6,
    "goals": 5,
    "assists": 6,
    "points": 11,
    "plus_minus": 0,
    "penalty_minutes": 6,
    "shots": 0,
    "shooting_percentage": 0,
    "avg_toi": "",
    "power_play_goals": 0,
    "power_play_points": 0,
    "short_handed_goals": 0,
    "game_winning_goals": 0,
    "faceoff_pct": null
  },
  "featured_stats": {
    "season": 20242025,
    "regularSeason": {
      "subSeason": {
        "assists": 18,
        "gameWinningGoals": 2,
        "gamesPlayed": 80,
        "goals": 13,
        "otGoals": 1,
        "pim": 32,
        "plusMinus": -18,
        "points": 31,
        "powerPlayGoals": 0,
        "powerPlayPoints": 0,
        "shootingPctg": 0.104,
        "shorthandedGoals": 1,
        "shorthandedPoints": 2,
        "shots": 125
      },
      "career": {
        "assists": 161,
        "gameWinningGoals": 9,
        "gamesPlayed": 681,
        "goals": 108,
        "otGoals": 3,
        "pim": 397,
        "plusMinus": -43,
        "points": 269,
        "powerPlayGoals": 6,
        "powerPlayPoints": 16,
        "shootingPctg": 0.09609999999999999,
        "shorthandedGoals": 10,
        "shorthandedPoints": 23,
        "shots": 1123
      }
    },
    "playoffs": {
      "subSeason": {
        "assists": 2,
        "gameWinningGoals": 0,
        "gamesPlayed": 13,
        "goals": 0,
        "otGoals": 0,
        "pim": 8,
        "plusMinus": -3,
        "points": 2,
        "powerPlayGoals": 0,
        "powerPlayPoints": 0,
        "shootingPctg": 0.0,
        "shorthandedGoals": 0,
        "shorthandedPoints": 0,
        "shots": 6
      },
      "career": {
        "assists": 6,
        "gameWinningGoals": 1,
        "gamesPlayed": 37,
        "goals": 6,
        "otGoals": 1,
        "pim": 35,
        "plusMinus": -1,
        "points": 12,
        "powerPlayGoals": 0,
        "powerPlayPoints": 0,
        "shootingPctg": 0.1578,
        "shorthandedGoals": 0,
        "shorthandedPoints": 0,
        "shots": 38
      }
    }
  },
  "career_totals": {
    "regular_season": {
      "seasons": 0,
      "games_played": 681,
      "goals": 108,
      "assists": 161,
      "points": 269,
      "plus_minus": -43,
      "penalty_minutes": 397
    },
    "playoffs": {
      "seasons": 0,
      "games_played": 37,
      "goals": 6,
      "assists": 6,
      "points": 12
    }
  },
  "recent_performance": {
    "last_5_games": [
      {
        "assists": 0,
        "gameDate": "2025-05-18",
        "gameId": 2024030217,
        "gameTypeId": 3,
        "goals": 0,
        "homeRoadFlag": "H",
        "opponentAbbrev": "FLA",
        "pim": 0,
        "plusMinus": 0,
        "points": 0,
        "powerPlayGoals": 0,
        "shifts": 22,
        "shorthandedGoals": 0,
        "shots": 1,
        "teamAbbrev": "TOR",
        "toi": "13:43"
      },
      {
        "assists": 0,
        "gameDate": "2025-05-16",
        "gameId": 2024030216,
        "gameTypeId": 3,
        "goals": 0,
        "homeRoadFlag": "R",
        "opponentAbbrev": "FLA",
        "pim": 0,
        "plusMinus": 0,
        "points": 0,
        "powerPlayGoals": 0,
        "shifts": 24,
        "shorthandedGoals": 0,
        "shots": 0,
        "teamAbbrev": "TOR",
        "toi": "15:37"
      },
      {
        "assists": 0,
        "gameDate": "2025-05-14",
        "gameId": 2024030215,
        "gameTypeId": 3,
        "goals": 0,
        "homeRoadFlag": "H",
        "opponentAbbrev": "FLA",
        "pim": 2,
        "plusMinus": -2,
        "points": 0,
        "powerPlayGoals": 0,
        "shifts": 21,
        "shorthandedGoals": 0,
        "shots": 0,
        "teamAbbrev": "TOR",
        "toi": "14:11"
      },
      {
        "assists": 0,
        "gameDate": "2025-05-11",
        "gameId": 2024030214,
        "gameTypeId": 3,
        "goals": 0,
        "homeRoadFlag": "R",
        "opponentAbbrev": "FLA",
        "pim": 0,
        "plusMinus": 0,
        "points": 0,
        "powerPlayGoals": 0,
        "shifts": 17,
        "shorthandedGoals": 0,
        "shots": 1,
        "teamAbbrev": "TOR",
        "toi": "11:28"
      },
      {
        "assists": 0,
        "gameDate": "2025-05-09",
        "gameId": 2024030213,
        "gameTypeId": 3,
        "goals": 0,
        "homeRoadFlag": "R",
        "opponentAbbrev": "FLA",
        "pim": 0,
        "plusMinus": 0,
        "points": 0,
        "powerPlayGoals": 0,
        "shifts": 21,
        "shorthandedGoals": 0,
        "shots": 1,
        "teamAbbrev": "TOR",
        "toi": "13:22"
      }
    ],
    "last_5_summary": {
      "games_played": 5,
      "total_goals": 0,
      "total_assists": 0,
      "total_points": 0,
      "avg_points": 0.0,
      "point_streak": 0
    }
  }
}